[
    { "id": 1, "image_url": "./assets/Agro_images/image_placeholder.jpeg", "name": "Makerel", "seller": "SeaFlavor Market", "price": 9.99, "category": "seafood" },
    { "id": 2, "image_url": "./assets/Agro_images/image_placeholder.jpeg", "name": "Carrot", "seller": "Fresh Fields Harvest Co.", "price": 9.99, "category": "vegetables" },
    { "id": 3, "image_url": "./assets/Agro_images/image_placeholder.jpeg", "name": "Eggs", "seller": "Moo & More Dairy Co.", "price": 2.99, "category": "dairy" },
    { "id": 4, "image_url": "./assets/Agro_images/image_placeholder.jpeg", "name": "Wheat Seeds", "seller": "Legumelight Farms", "price": 5.99, "category": "seeds" },
    { "id": 5, "image_url": "./assets/Agro_images/image_placeholder.jpeg", "name": "Pesticide", "seller": "AgroAid Solutions", "price": 15.99, "category": "chemicals" },
    { "id": 6, "image_url": "./assets/Agro_images/image_placeholder.jpeg", "name": "Tomato Seeds", "seller": "SproutSource Emporium", "price": 3.99, "category": "seeds" },
    { "id": 7, "image_url": "./assets/Agro_images/image_placeholder.jpeg", "name": "Pest Control", "seller": "AgroAdvantage Consultants", "price": 49.99, "category": "services" },
    { "id": 8, "image_url": "./assets/Agro_images/image_placeholder.jpeg", "name": "Phosphorus Fertilizer", "seller": "Fertile Fields Co.", "price": 29.99, "category": "fertilizers" },
    { "id": 9, "image_url": "./assets/Agro_images/image_placeholder.jpeg", "name": "Corn Seeds", "seller": "SeedMaster Co.", "price": 7.99, "category": "seeds" },
    { "id": 10, "image_url": "./assets/Agro_images/image_placeholder.jpeg", "name": "Cinnamon", "seller": "Spice World Inc.", "price": 5.99, "category": "spices" },
    { "id": 11, "image_url": "./assets/Agro_images/image_placeholder.jpeg", "name": "Tractor", "seller": "FarmWorks Equipment", "price": 5000.00, "category": "equipment" },
    { "id": 12, "image_url": "./assets/Agro_images/image_placeholder.jpeg", "name": "Smart Irrigation System", "seller": "AgroTech Solutions", "price": 1500.00, "category": "technology" },
    { "id": 13, "image_url": "./assets/Agro_images/image_placeholder.jpeg", "name": "Work Boots", "seller": "FarmGear Inc.", "price": 79.99, "category": "clothing" },
    { "id": 14, "image_url": "./assets/Agro_images/image_placeholder.jpeg", "name": "Apples", "seller": "Fresh Fields Harvest Co.", "price": 1.99, "category": "fruits" },
    { "id": 15, "image_url": "./assets/Agro_images/image_placeholder.jpeg", "name": "Beef Steak", "seller": "Prime Cuts Butcher", "price": 12.99, "category": "meat" },
    { "id": 16, "image_url": "./assets/Agro_images/image_placeholder.jpeg", "name": "Consulting Services", "seller": "AgroAdvantage Consultants", "price": 200.00, "category": "services" },
    { "id": 17, "image_url": "./assets/Agro_images/image_placeholder.jpeg", "name": "Nitrogen Fertilizer", "seller": "AgroAid Solutions", "price": 15.99, "category": "fertilizers" },
    { "id": 18, "image_url": "./assets/Agro_images/image_placeholder.jpeg", "name": "Lettuce Seedlings", "seller": "Green Thumb Nursery", "price": 4.99, "category": "seeds" },
    { "id": 19, "image_url": "./assets/Agro_images/image_placeholder.jpeg", "name": "Oregano", "seller": "Herb Garden Grocers", "price": 3.99, "category": "spices" },
    { "id": 20, "image_url": "./assets/Agro_images/image_placeholder.jpeg", "name": "Harvester", "seller": "AgroTech Machinery", "price": 10000.00, "category": "equipment" },
    { "id": 21, "image_url": "./assets/Agro_images/image_placeholder.jpeg", "name": "Drone", "seller": "AgroDrone Technologies", "price": 3000.00, "category": "technology" },
    { "id": 22, "image_url": "./assets/Agro_images/image_placeholder.jpeg", "name": "Sun Hat", "seller": "SunSafe Hats", "price": 24.99, "category": "clothing" },
    { "id": 23, "image_url": "./assets/Agro_images/image_placeholder.jpeg", "name": "Mangoes", "seller": "Fresh Fields Harvest Co.", "price": 2.49, "category": "fruits" },
    { "id": 24, "image_url": "./assets/Agro_images/image_placeholder.jpeg", "name": "Milk", "seller": "Moo & More Dairy Co.", "price": 3.49, "category": "dairy" },
    { "id": 25, "image_url": "./assets/Agro_images/big watering can.jpg", "name": "Chicken", "seller": "Poultry Palace Market", "price": 8.99, "category": "meat" }
  ]